{"fle.paris":[{"target":"eurogoodies.dover","urgency":0,"shortest_distance_km":258,"ferry_time":35,"ferry_price":300,"cargo":"cargo.frsh_herbs","company_truck":"mercedes_actros_2014_6x2_a","trailer_variant":"trailer.scs_ref_a","trailer_definition":"trailer_def.scs.box.single_3.reefer","units_count":33,"fill_ratio":1,"trailer_place":0}],"kaarfor.strasbourg":[{"target":"te_logistica.cagliari","urgency":2,"shortest_distance_km":1310,"ferry_time":840,"ferry_price":879,"cargo":"cargo.used_packag","company_truck":"scania_s_6x2_450","trailer_variant":"trailer.scs_dry_ms","trailer_definition":"trailer_def.scs.box.single_3.dryvan_m","units_count":33,"fill_ratio":1,"trailer_place":0}],"cargotras.sassari":[{"target":"cesare_smar.palermo","urgency":0,"shortest_distance_km":228,"ferry_time":720,"ferry_price":778,"cargo":"cargo.pasta","company_truck":"mercedes_actros_2014_4x2_a","trailer_variant":"trailer.scs_dry_ms","trailer_definition":"trailer_def.scs.box.single_3.dryvan_m","units_count":33,"fill_ratio":1,"trailer_place":0},{"target":"te_logistica.sassari","urgency":0,"shortest_distance_km":1,"ferry_time":0,"ferry_price":0,"cargo":"cargo.straw_bales","company_truck":"scania_streamline_6x2_b","trailer_variant":"trailer.scs_dry_a","trailer_definition":"trailer_def.scs.box.single_3.dryvan","units_count":33,"fill_ratio":1,"trailer_place":0}],"costruzi_win.palermo":[{"target":"sal.sassari","urgency":1,"shortest_distance_km":254,"ferry_time":720,"ferry_price":778,"cargo":"cargo.forklifts","company_truck":"man_6x4_b","trailer_variant":"trailer.scs_lowbed_4","trailer_definition":"trailer_def.scs.lowbed.single_4_sh.short","units_count":1,"fill_ratio":1,"trailer_place":0}],"marmo.firenze":[{"target":"cargotras.livorno","urgency":0,"shortest_distance_km":136,"ferry_time":0,"ferry_price":0,"cargo":"cargo.digger1000","company_truck":"man_4x2_c","trailer_variant":"trailer.scs_lowbed_3","trailer_definition":"trailer_def.scs.lowbed.single_3.short","units_count":1,"fill_ratio":1,"trailer_place":0},{"target":"costruzi_bas.firenze","urgency":1,"shortest_distance_km":154,"ferry_time":0,"ferry_price":0,"cargo":"cargo.marb_blck2","company_truck":"renault_t_4x2h","trailer_variant":"trailer.scs_flat_r","trailer_definition":"trailer_def.scs.flatbed.single_3.flatbed_w","units_count":2,"fill_ratio":1,"trailer_place":0}],"ika_bohag.pescara":[{"target":"exomar.roma","urgency":2,"shortest_distance_km":223,"ferry_time":0,"ferry_price":0,"cargo":"cargo.used_packag","company_truck":"iveco_4x2_a","trailer_variant":"trailer.scs_dry_ms","trailer_definition":"trailer_def.scs.box.single_3.dryvan_m","units_count":33,"fill_ratio":1,"trailer_place":0},{"target":"cnp.ancona","urgency":1,"shortest_distance_km":207,"ferry_time":0,"ferry_price":0,"cargo":"cargo.empty_palet","company_truck":"man_tgx_euro6_6x4_xlx","trailer_variant":"trailer.scs_dry_ms","trailer_definition":"trailer_def.scs.box.single_3.dryvan_m","units_count":33,"fill_ratio":1,"trailer_place":0}],"tesore_gust.firenze":[{"target":"exomar.bologna","urgency":1,"shortest_distance_km":221,"ferry_time":0,"ferry_price":0,"cargo":"cargo.vinegar","company_truck":"renault_magnum_6x4_a","trailer_variant":"trailer.scs_dry_ms","trailer_definition":"trailer_def.scs.box.single_3.dryvan_m","units_count":33,"fill_ratio":1,"trailer_place":0}],"stokes.dusseldorf":[{"target":"cont_port_it.napoli","urgency":1,"shortest_distance_km":1743,"ferry_time":0,"ferry_price":0,"cargo":"cargo.clothes_c","company_truck":"man_6x4_b","trailer_variant":"trailer.scs_gosck40","trailer_definition":"trailer_def.scs.gooseneck.singl_3e_40.container","units_count":30,"fill_ratio":1,"trailer_place":0}],"cesare_smar.sassari":[{"target":"cargotras.palermo","urgency":1,"shortest_distance_km":229,"ferry_time":720,"ferry_price":778,"cargo":"cargo.empty_palet","company_truck":"scania_r_4x2_520","trailer_variant":"trailer.scs_dry","trailer_definition":"trailer_def.scs.box.single_3.dryvan","units_count":33,"fill_ratio":1,"trailer_place":0},{"target":"cargotras.livorno","urgency":0,"shortest_distance_km":804,"ferry_time":840,"ferry_price":879,"cargo":"cargo.used_plast_c","company_truck":"man_6x4_b","trailer_variant":"trailer.scs_flat_c_r","trailer_definition":"trailer_def.scs.flatbed.single_3.container","units_count":33,"fill_ratio":1,"trailer_place":0}],"costruzi_hal.sassari":[{"target":"marmo.sassari","urgency":0,"shortest_distance_km":44,"ferry_time":0,"ferry_price":0,"cargo":"cargo.hipresstank","company_truck":"renault_premium_4x2_a","trailer_variant":"trailer.scs_flat_b","trailer_definition":"trailer_def.scs.flatbed.single_3.flatbed_w","units_count":2,"fill_ratio":1,"trailer_place":0}],"costruzi_fla.catanzaro":[{"target":"cnp.catania","urgency":1,"shortest_distance_km":327,"ferry_time":20,"ferry_price":347,"cargo":"cargo.empty_palet","company_truck":"daf_xf_euro6_6x4_c","trailer_variant":"trailer.scs_dry_ms","trailer_definition":"trailer_def.scs.box.single_3.dryvan_m","units_count":33,"fill_ratio":1,"trailer_place":0}],"ika_bohag.napoli":[{"target":"tras_med.bari","urgency":2,"shortest_distance_km":246,"ferry_time":0,"ferry_price":0,"cargo":"cargo.used_packag","company_truck":"iveco_4x2_c","trailer_variant":"trailer.scs_dry_a","trailer_definition":"trailer_def.scs.box.single_3.dryvan","units_count":33,"fill_ratio":1,"trailer_place":0}],"vitas_pwr.taranto":[{"target":"cargotras.catanzaro","urgency":1,"shortest_distance_km":292,"ferry_time":0,"ferry_price":0,"cargo":"cargo.empty_palet","company_truck":"scania_6x4_a","trailer_variant":"trailer.scs_dry","trailer_definition":"trailer_def.scs.box.single_3.dryvan","units_count":33,"fill_ratio":1,"trailer_place":0}],"sal.sassari":[{"target":"costruzi_fla.catanzaro","urgency":0,"shortest_distance_km":535,"ferry_time":740,"ferry_price":1125,"cargo":"cargo.lumber","company_truck":"renault_magnum_4x2_a","trailer_variant":"trailer.scs_flat_c_g","trailer_definition":"trailer_def.scs.flatbed.single_3.container","units_count":2,"fill_ratio":1,"trailer_place":0}],"cont_port_it.livorno":[{"target":"libellula.livorno","urgency":1,"shortest_distance_km":42,"ferry_time":0,"ferry_price":0,"cargo":"cargo.motor_oil_c","company_truck":"scania_r_6x4_650","trailer_variant":"trailer.scs_gosck40","trailer_definition":"trailer_def.scs.gooseneck.singl_3e_40.container","units_count":30,"fill_ratio":1,"trailer_place":0},{"target":"te_logistica.parma","urgency":2,"shortest_distance_km":270,"ferry_time":0,"ferry_price":0,"cargo":"cargo.carrots_c","company_truck":"daf_xf_euro6_6x2_a","trailer_variant":"trailer.scs_gosck20","trailer_definition":"trailer_def.scs.gooseneck.singl_3e_20.container","units_count":15,"fill_ratio":1,"trailer_place":0}],"costruzi_win.pescara":[{"target":"tesore_gust.napoli","urgency":1,"shortest_distance_km":250,"ferry_time":0,"ferry_price":0,"cargo":"cargo.empty_palet","company_truck":"renault_magnum_6x4_a","trailer_variant":"trailer.scs_dry_s","trailer_definition":"trailer_def.scs.box.single_3.dryvan","units_count":33,"fill_ratio":1,"trailer_place":0}],"tras_med.catania":[{"target":"exomar.roma","urgency":0,"shortest_distance_km":794,"ferry_time":20,"ferry_price":347,"cargo":"cargo.tomatoes","company_truck":"scania_s_6x4_730","trailer_variant":"trailer.scs_ins_a","trailer_definition":"trailer_def.scs.box.single_3.insulated","units_count":33,"fill_ratio":1,"trailer_place":0}],"tradeaux.paris":[{"target":"exomar.bologna","urgency":2,"shortest_distance_km":1236,"ferry_time":0,"ferry_price":0,"cargo":"cargo.used_packag","company_truck":"scania_r_6x4_650","trailer_variant":"trailer.scs_dry_s","trailer_definition":"trailer_def.scs.box.single_3.dryvan","units_count":33,"fill_ratio":1,"trailer_place":0}],"ika_bohag.catania":[{"target":"tras_med.roma","urgency":2,"shortest_distance_km":806,"ferry_time":20,"ferry_price":347,"cargo":"cargo.used_packag","company_truck":"scania_r_6x2_450","trailer_variant":"trailer.scs_curt_s","trailer_definition":"trailer_def.scs.box.single_3.curtain","units_count":33,"fill_ratio":1,"trailer_place":0}],"cargotras.livorno":[{"target":"tras_med.genova","urgency":2,"shortest_distance_km":250,"ferry_time":0,"ferry_price":0,"cargo":"cargo.mondeos","company_truck":"mercedes_actros_2014_4x2_c","trailer_variant":"trailer.car_trans3","trailer_definition":"trailer_def.mondeos.car_trans3","units_count":100,"fill_ratio":1,"trailer_place":0},{"target":"libellula.bologna","urgency":1,"shortest_distance_km":209,"ferry_time":0,"ferry_price":0,"cargo":"cargo.forklifts","company_truck":"man_tgx_euro6_4x2_xl","trailer_variant":"trailer.scs_lowbed_4","trailer_definition":"trailer_def.scs.lowbed.single_4_sh.short","units_count":1,"fill_ratio":1,"trailer_place":0}],"te_logistica.parma":[{"target":"eolo_lines.napoli","urgency":0,"shortest_distance_km":688,"ferry_time":0,"ferry_price":0,"cargo":"cargo.oil_filt_c","company_truck":"scania_s_6x4_730","trailer_variant":"trailer.scs_gosck40","trailer_definition":"trailer_def.scs.gooseneck.singl_3e_40.container","units_count":30,"fill_ratio":1,"trailer_place":0}],"piac.cassino":[{"target":"te_logistica.cagliari","urgency":1,"shortest_distance_km":149,"ferry_time":840,"ferry_price":879,"cargo":"cargo.used_battery","company_truck":"scania_streamline_4x2_a","trailer_variant":"trailer.scs_curt_a","trailer_definition":"trailer_def.scs.box.single_3.curtain","units_count":33,"fill_ratio":1,"trailer_place":0},{"target":"te_logistica.sassari","urgency":0,"shortest_distance_km":352,"ferry_time":840,"ferry_price":879,"cargo":"cargo.used_plast_c","company_truck":"iveco_4x2_c","trailer_variant":"trailer.scs_flat_c_g","trailer_definition":"trailer_def.scs.flatbed.single_3.container","units_count":33,"fill_ratio":1,"trailer_place":0},{"target":"exomar.roma","urgency":2,"shortest_distance_km":138,"ferry_time":0,"ferry_price":0,"cargo":"cargo.used_packag","company_truck":"scania_s_6x4_730","trailer_variant":"trailer.scs_dry_a","trailer_definition":"trailer_def.scs.box.single_3.dryvan","units_count":33,"fill_ratio":1,"trailer_place":0}],"eurogoodies.wien":[{"target":"exomar.roma","urgency":0,"shortest_distance_km":1110,"ferry_time":0,"ferry_price":0,"cargo":"cargo.goat_cheese","company_truck":"iveco_h_4x2_a","trailer_variant":"trailer.scs_ref","trailer_definition":"trailer_def.scs.box.single_3.reefer","units_count":33,"fill_ratio":1,"trailer_place":1}],"exomar.ancona":[{"target":"tras_med.roma","urgency":0,"shortest_distance_km":254,"ferry_time":0,"ferry_price":0,"cargo":"cargo.overweight","company_truck":"man_tgx_euro6_6x4_xlx","trailer_variant":"trailer.scs_lowbed41","trailer_definition":"trailer_def.scs.lowbed.single_41_ln.long","units_count":1,"fill_ratio":1,"trailer_place":0}],"fui.catanzaro":[{"target":"te_logistica.napoli","urgency":1,"shortest_distance_km":249,"ferry_time":0,"ferry_price":0,"cargo":"cargo.carrots","company_truck":"mercedes_4x2_b","trailer_variant":"trailer.scs_dry_s","trailer_definition":"trailer_def.scs.box.single_3.dryvan","units_count":33,"fill_ratio":1,"trailer_place":0},{"target":"cesare_smar.palermo","urgency":0,"shortest_distance_km":459,"ferry_time":20,"ferry_price":347,"cargo":"cargo.pesto","company_truck":"man_6x4_b","trailer_variant":"trailer.scs_curt_a","trailer_definition":"trailer_def.scs.box.single_3.curtain","units_count":33,"fill_ratio":1,"trailer_place":0}],"tras_med.cagliari":[{"target":"exomar.olbia","urgency":0,"shortest_distance_km":244,"ferry_time":0,"ferry_price":0,"cargo":"cargo.straw_bales","company_truck":"man_6x4_b","trailer_variant":"trailer.scs_flat_c_r","trailer_definition":"trailer_def.scs.flatbed.single_3.container","units_count":33,"fill_ratio":1,"trailer_place":0}],"transinet.rotterdam":[{"target":"tradeaux.lille","urgency":0,"shortest_distance_km":224,"ferry_time":0,"ferry_price":0,"cargo":"cargo.sq_tub","company_truck":"man_6x4_b","trailer_variant":"trailer.scs_flat_r","trailer_definition":"trailer_def.scs.flatbed.single_3.flatbed_w","units_count":2,"fill_ratio":1,"trailer_place":0}],"cont_port_it.bari":[{"target":"cargotras.catanzaro","urgency":0,"shortest_distance_km":327,"ferry_time":0,"ferry_price":0,"cargo":"cargo.used_plast_c","company_truck":"mercedes_4x2","trailer_variant":"trailer.scs_gosck220","trailer_definition":"trailer_def.scs.gooseneck.singl_3e_220.container","units_count":30,"fill_ratio":1,"trailer_place":0}],"acc.terni":[{"target":"cnp.ancona","urgency":2,"shortest_distance_km":157,"ferry_time":0,"ferry_price":0,"cargo":"cargo.fueltanker","company_truck":"man_tgx_euro6_4x2_xl","trailer_variant":"trailer.scs_gosck220","trailer_definition":"trailer_def.scs.gooseneck.singl_3e_220.container","units_count":80,"fill_ratio":1,"trailer_place":0},{"target":"costruzi_fla.catanzaro","urgency":0,"shortest_distance_km":684,"ferry_time":0,"ferry_price":0,"cargo":"cargo.outdr_flr_tl","company_truck":"iveco_h_4x2_a","trailer_variant":"trailer.scs_dry_a","trailer_definition":"trailer_def.scs.box.single_3.dryvan","units_count":33,"fill_ratio":1,"trailer_place":0},{"target":"te_logistica.napoli","urgency":1,"shortest_distance_km":346,"ferry_time":0,"ferry_price":0,"cargo":"cargo.floorpanels","company_truck":"daf_4x2_b","trailer_variant":"trailer.panel_trans.floor","trailer_definition":"trailer_def.floorpanels.panel_trans.floor","units_count":99,"fill_ratio":1,"trailer_place":0}],"stokes.liege":[{"target":"sanbuilders.luxembourg","urgency":0,"shortest_distance_km":148,"ferry_time":0,"ferry_price":0,"cargo":"cargo.sq_tub","company_truck":"scania_streamline_4x2_b","trailer_variant":"trailer.scs_flat_b","trailer_definition":"trailer_def.scs.flatbed.single_3.flatbed_w","units_count":2,"fill_ratio":1,"trailer_place":0}],"ika_bohag.roma":[{"target":"cnp.taranto","urgency":1,"shortest_distance_km":504,"ferry_time":0,"ferry_price":0,"cargo":"cargo.empty_palet","company_truck":"renault_premium_4x2_c","trailer_variant":"trailer.scs_dry_ms","trailer_definition":"trailer_def.scs.box.single_3.dryvan_m","units_count":33,"fill_ratio":1,"trailer_place":0}],"cont_port_it.napoli":[{"target":"eolo_lines.messina","urgency":2,"shortest_distance_km":449,"ferry_time":20,"ferry_price":347,"cargo":"cargo.exhausts_c","company_truck":"daf_4x2_b","trailer_variant":"trailer.scs_flat_c_r","trailer_definition":"trailer_def.scs.flatbed.single_3.container","units_count":33,"fill_ratio":1,"trailer_place":0}],"tras_med.bari":[{"target":"eolo_lines.messina","urgency":1,"shortest_distance_km":427,"ferry_time":20,"ferry_price":347,"cargo":"cargo.oil_filters","company_truck":"iveco_4x2_a","trailer_variant":"trailer.scs_curt_s","trailer_definition":"trailer_def.scs.box.single_3.curtain","units_count":33,"fill_ratio":1,"trailer_place":0},{"target":"cesare_smar.sassari","urgency":1,"shortest_distance_km":466,"ferry_time":840,"ferry_price":879,"cargo":"cargo.gnocchi","company_truck":"mercedes_actros_2014_6x2_a","trailer_variant":"trailer.scs_ref","trailer_definition":"trailer_def.scs.box.single_3.reefer","units_count":33,"fill_ratio":1,"trailer_place":0}],"acc.catania":[{"target":"exomar.olbia","urgency":0,"shortest_distance_km":460,"ferry_time":720,"ferry_price":778,"cargo":"cargo.outdr_flr_tl","company_truck":"daf_4x2_b","trailer_variant":"trailer.scs_brick_y","trailer_definition":"trailer_def.scs.flatbed.single_3.brick","units_count":33,"fill_ratio":1,"trailer_place":0},{"target":"c_navale.messina","urgency":0,"shortest_distance_km":142,"ferry_time":0,"ferry_price":0,"cargo":"cargo.hipresstank","company_truck":"renault_premium_4x2_a","trailer_variant":"trailer.scs_flat_b","trailer_definition":"trailer_def.scs.flatbed.single_3.flatbed_w","units_count":2,"fill_ratio":1,"trailer_place":0},{"target":"exomar.roma","urgency":2,"shortest_distance_km":794,"ferry_time":20,"ferry_price":347,"cargo":"cargo.seal_bearing","company_truck":"scania_streamline_4x2_b","trailer_variant":"trailer.scs_curt","trailer_definition":"trailer_def.scs.box.single_3.curtain","units_count":33,"fill_ratio":1,"trailer_place":0},{"target":"cargotras.palermo","urgency":2,"shortest_distance_km":203,"ferry_time":0,"ferry_price":0,"cargo":"cargo.fueltanker","company_truck":"iveco_4x2_a","trailer_variant":"trailer.scs_flat_c_g","trailer_definition":"trailer_def.scs.flatbed.single_3.container","units_count":87,"fill_ratio":1,"trailer_place":0}],"stokes.zurich":[{"target":"posped.koln","urgency":0,"shortest_distance_km":584,"ferry_time":0,"ferry_price":0,"cargo":"cargo.sq_tub","company_truck":"renault_magnum_6x4_a","trailer_variant":"trailer.scs_flat_b","trailer_definition":"trailer_def.scs.flatbed.single_3.flatbed_w","units_count":2,"fill_ratio":1,"trailer_place":0}],"marmo.livorno":[{"target":"fui.roma","urgency":2,"shortest_distance_km":391,"ferry_time":0,"ferry_price":0,"cargo":"cargo.excav_soil","company_truck":"mercedes_actros_2014_6x2_a","trailer_variant":"trailer.s_ki_solid.cover","trailer_definition":"trailer_def.excav_soil.s_ki_solid.cover","units_count":100,"fill_ratio":1,"trailer_place":0}],"aaa.pescara":[{"target":"exomar.roma","urgency":2,"shortest_distance_km":240,"ferry_time":0,"ferry_price":0,"cargo":"cargo.scooters","company_truck":"mercedes_4x2","trailer_variant":"trailer.scs_curt","trailer_definition":"trailer_def.scs.box.single_3.curtain","units_count":33,"fill_ratio":1,"trailer_place":0}],"fattoria_f.napoli":[{"target":"tras_med.cagliari","urgency":1,"shortest_distance_km":218,"ferry_time":840,"ferry_price":879,"cargo":"cargo.beef_meat","company_truck":"scania_s_6x4_730","trailer_variant":"trailer.scs_ref_a","trailer_definition":"trailer_def.scs.box.single_3.reefer","units_count":33,"fill_ratio":1,"trailer_place":0},{"target":"exomar.taranto","urgency":1,"shortest_distance_km":299,"ferry_time":0,"ferry_price":0,"cargo":"cargo.milk","company_truck":"daf_xf_euro6_6x4_c","trailer_variant":"trailer.scs_curt","trailer_definition":"trailer_def.scs.box.single_3.curtain","units_count":33,"fill_ratio":1,"trailer_place":0}],"kaarfor.bern":[{"target":"tras_med.roma","urgency":1,"shortest_distance_km":919,"ferry_time":0,"ferry_price":0,"cargo":"cargo.empty_palet","company_truck":"scania_streamline_4x2_c","trailer_variant":"trailer.scs_dry","trailer_definition":"trailer_def.scs.box.single_3.dryvan","units_count":33,"fill_ratio":1,"trailer_place":0}],"cnp.catania":[{"target":"acc.catania","urgency":2,"shortest_distance_km":51,"ferry_time":0,"ferry_price":0,"cargo":"cargo.kerosene","company_truck":"iveco_h_4x2_a","trailer_variant":"trailer.fuel_cistern","trailer_definition":"trailer_def.kerosene.fuel_cistern","units_count":100,"fill_ratio":1,"trailer_place":0},{"target":"cargotras.catanzaro","urgency":0,"shortest_distance_km":344,"ferry_time":20,"ferry_price":347,"cargo":"cargo.oil","company_truck":"scania_4x2_c","trailer_variant":"trailer.fuel_cistern","trailer_definition":"trailer_def.oil.fuel_cistern","units_count":100,"fill_ratio":1,"trailer_place":0}],"te_logistica.firenze":[{"target":"tras_med.genova","urgency":0,"shortest_distance_km":268,"ferry_time":0,"ferry_price":0,"cargo":"cargo.olive_oil_t","company_truck":"renault_premium_4x2_c","trailer_variant":"trailer.scs_fodt","trailer_definition":"trailer_def.scs.foodtank.single_3.paint","units_count":30,"fill_ratio":1,"trailer_place":0}],"eurogoodies.dijon":[{"target":"cargotras.olbia","urgency":2,"shortest_distance_km":766,"ferry_time":1050,"ferry_price":1548,"cargo":"cargo.yogurt","company_truck":"renault_premium_6x4_a","trailer_variant":"trailer.scs_ins_a","trailer_definition":"trailer_def.scs.box.single_3.insulated","units_count":33,"fill_ratio":1,"trailer_place":0}],"spinelli.parma":[{"target":"te_logistica.parma","urgency":2,"shortest_distance_km":18,"ferry_time":0,"ferry_price":0,"cargo":"cargo.used_packag","company_truck":"man_6x4_b","trailer_variant":"trailer.scs_curt","trailer_definition":"trailer_def.scs.box.single_3.curtain","units_count":33,"fill_ratio":1,"trailer_place":0}],"fui.firenze":[{"target":"cargotras.livorno","urgency":0,"shortest_distance_km":153,"ferry_time":0,"ferry_price":0,"cargo":"cargo.tomatoes","company_truck":"mercedes_4x2_a","trailer_variant":"trailer.scs_ins_a","trailer_definition":"trailer_def.scs.box.single_3.insulated","units_count":33,"fill_ratio":1,"trailer_place":0}],"quadrelli.bari":[{"target":"cargotras.sassari","urgency":2,"shortest_distance_km":468,"ferry_time":840,"ferry_price":879,"cargo":"cargo.gravel","company_truck":"mercedes_6x2_b","trailer_variant":"trailer.s_ki_solid.gravel","trailer_definition":"trailer_def.gravel.s_ki_solid.gravel","units_count":100,"fill_ratio":1,"trailer_place":0},{"target":"fui.catanzaro","urgency":2,"shortest_distance_km":196,"ferry_time":0,"ferry_price":0,"cargo":"cargo.excav_soil","company_truck":"scania_s_6x2_450","trailer_variant":"trailer.s_ki_solid.cover","trailer_definition":"trailer_def.excav_soil.s_ki_solid.cover","units_count":100,"fill_ratio":1,"trailer_place":0}],"sal.terni":[{"target":"exomar.ancona","urgency":1,"shortest_distance_km":188,"ferry_time":0,"ferry_price":0,"cargo":"cargo.sawpanels","company_truck":"iveco_4x2_b","trailer_variant":"trailer.scs_dry","trailer_definition":"trailer_def.scs.box.single_3.dryvan","units_count":33,"fill_ratio":1,"trailer_place":0}],"costruzi_win.taranto":[{"target":"exomar.roma","urgency":1,"shortest_distance_km":429,"ferry_time":0,"ferry_price":0,"cargo":"cargo.empty_palet","company_truck":"man_6x4_b","trailer_variant":"trailer.scs_dry_a","trailer_definition":"trailer_def.scs.box.single_3.dryvan","units_count":33,"fill_ratio":1,"trailer_place":0},{"target":"fui.catanzaro","urgency":1,"shortest_distance_km":149,"ferry_time":0,"ferry_price":0,"cargo":"cargo.forklifts","company_truck":"scania_streamline_4x2_c","trailer_variant":"trailer.scs_lowbed41","trailer_definition":"trailer_def.scs.lowbed.single_41_ln.long","units_count":1,"fill_ratio":1,"trailer_place":0}],"te_logistica.cagliari":[{"target":"cesare_smar.sassari","urgency":0,"shortest_distance_km":205,"ferry_time":0,"ferry_price":0,"cargo":"cargo.beverages_c","company_truck":"iveco_6x2_a","trailer_variant":"trailer.scs_flat_c_r","trailer_definition":"trailer_def.scs.flatbed.single_3.container","units_count":33,"fill_ratio":1,"trailer_place":0},{"target":"fui.olbia","urgency":1,"shortest_distance_km":194,"ferry_time":0,"ferry_price":0,"cargo":"cargo.fertilizer","company_truck":"scania_r_4x2_370","trailer_variant":"trailer.scs_brick_y","trailer_definition":"trailer_def.scs.flatbed.single_3.brick","units_count":33,"fill_ratio":1,"trailer_place":0}],"costruzi_bas.firenze":[{"target":"marmo.livorno","urgency":0,"shortest_distance_km":137,"ferry_time":0,"ferry_price":0,"cargo":"cargo.hipresstank","company_truck":"daf_xf_euro6_6x2_a","trailer_variant":"trailer.scs_flat_r","trailer_definition":"trailer_def.scs.flatbed.single_3.flatbed_w","units_count":2,"fill_ratio":1,"trailer_place":0},{"target":"fui.roma","urgency":2,"shortest_distance_km":331,"ferry_time":0,"ferry_price":0,"cargo":"cargo.excav_soil","company_truck":"daf_4x2_a","trailer_variant":"trailer.s_ki_solid.cover","trailer_definition":"trailer_def.excav_soil.s_ki_solid.cover","units_count":100,"fill_ratio":1,"trailer_place":0}],"aaa.taranto":[{"target":"cargotras.pescara","urgency":1,"shortest_distance_km":369,"ferry_time":0,"ferry_price":0,"cargo":"cargo.iveco_vans","company_truck":"daf_4x2_b","trailer_variant":"trailer.van_trans_id","trailer_definition":"trailer_def.iveco_vans.van_trans_id","units_count":100,"fill_ratio":1,"trailer_place":0},{"target":"exomar.olbia","urgency":2,"shortest_distance_km":544,"ferry_time":840,"ferry_price":879,"cargo":"cargo.scooters","company_truck":"man_6x4_b","trailer_variant":"trailer.scs_dry_m","trailer_definition":"trailer_def.scs.box.single_3.dryvan_m","units_count":33,"fill_ratio":1,"trailer_place":0}],"ika_bohag.bologna":[{"target":"exomar.taranto","urgency":2,"shortest_distance_km":789,"ferry_time":0,"ferry_price":0,"cargo":"cargo.used_packag","company_truck":"scania_streamline_6x4_a","trailer_variant":"trailer.scs_dry","trailer_definition":"trailer_def.scs.box.single_3.dryvan","units_count":33,"fill_ratio":1,"trailer_place":0}],"pp_chimica.olbia":[{"target":"acc.taranto","urgency":2,"shortest_distance_km":453,"ferry_time":840,"ferry_price":879,"cargo":"cargo.magnesium","company_truck":"mercedes_actros_2014_6x2_a","trailer_variant":"trailer.scs_flat_c_g","trailer_definition":"trailer_def.scs.flatbed.single_3.container","units_count":87,"fill_ratio":1,"trailer_place":0}],"kaarfor.munchen":[{"target":"cnp.napoli","urgency":1,"shortest_distance_km":1186,"ferry_time":0,"ferry_price":0,"cargo":"cargo.empty_palet","company_truck":"scania_streamline_4x2_c","trailer_variant":"trailer.scs_dry_s","trailer_definition":"trailer_def.scs.box.single_3.dryvan","units_count":33,"fill_ratio":1,"trailer_place":0}],"tradeaux.rostock":[{"target":"nbfc.berlin","urgency":0,"shortest_distance_km":213,"ferry_time":0,"ferry_price":0,"cargo":"cargo.sq_tub","company_truck":"renault_premium_6x4_a","trailer_variant":"trailer.scs_flat_c_r","trailer_definition":"trailer_def.scs.flatbed.single_3.container","units_count":1,"fill_ratio":1,"trailer_place":0}],"pp_chimica.roma":[{"target":"fui.catanzaro","urgency":1,"shortest_distance_km":425,"ferry_time":0,"ferry_price":0,"cargo":"cargo.potassium","company_truck":"man_4x2_a","trailer_variant":"trailer.scs_flat_c_r","trailer_definition":"trailer_def.scs.flatbed.single_3.container","units_count":87,"fill_ratio":1,"trailer_place":0}],"sal.livorno":[{"target":"cargotras.sassari","urgency":0,"shortest_distance_km":801,"ferry_time":840,"ferry_price":879,"cargo":"cargo.logs","company_truck":"scania_6x2_b","trailer_variant":"trailer.scs_log","trailer_definition":"trailer_def.scs.log.single_3.steel","units_count":2,"fill_ratio":1,"trailer_place":0}],"cnp.napoli":[{"target":"marmo.olbia","urgency":0,"shortest_distance_km":269,"ferry_time":840,"ferry_price":879,"cargo":"cargo.diesel","company_truck":"scania_6x4_a","trailer_variant":"trailer.willig.fuel_cistern","trailer_definition":"trailer_def.diesel.willig.fuel_cistern","units_count":100,"fill_ratio":1,"trailer_place":0},{"target":"cargotras.livorno","urgency":0,"shortest_distance_km":576,"ferry_time":0,"ferry_price":0,"cargo":"cargo.carbn_pwdr_c","company_truck":"mercedes_6x4_a","trailer_variant":"trailer.scs_flat_c_r","trailer_definition":"trailer_def.scs.flatbed.single_3.container","units_count":33,"fill_ratio":1,"trailer_place":0}],"spinelli.cassino":[{"target":"cargotras.pescara","urgency":2,"shortest_distance_km":198,"ferry_time":0,"ferry_price":0,"cargo":"cargo.scrap_metals","company_truck":"man_tgx_euro6_4x2_xxl","trailer_variant":"trailer.s_ki_solid.cover","trailer_definition":"trailer_def.scrap_metals.s_ki_solid.cover","units_count":100,"fill_ratio":1,"trailer_place":0},{"target":"tesore_gust.parma","urgency":1,"shortest_distance_km":555,"ferry_time":0,"ferry_price":0,"cargo":"cargo.empty_palet","company_truck":"man_4x2_a","trailer_variant":"trailer.scs_dry_ms","trailer_definition":"trailer_def.scs.box.single_3.dryvan_m","units_count":33,"fill_ratio":1,"trailer_place":0},{"target":"te_logistica.cagliari","urgency":2,"shortest_distance_km":184,"ferry_time":840,"ferry_price":879,"cargo":"cargo.used_packag","company_truck":"scania_6x4_a","trailer_variant":"trailer.scs_dry_s","trailer_definition":"trailer_def.scs.box.single_3.dryvan","units_count":33,"fill_ratio":1,"trailer_place":0}],"eolo_lines.palermo":[{"target":"te_logistica.messina","urgency":0,"shortest_distance_km":208,"ferry_time":0,"ferry_price":0,"cargo":"cargo.beverages_t","company_truck":"scania_r_6x2_450","trailer_variant":"trailer.scs_fodt","trailer_definition":"trailer_def.scs.foodtank.single_3.paint","units_count":27,"fill_ratio":1,"trailer_place":0},{"target":"te_logistica.cagliari","urgency":2,"shortest_distance_km":12,"ferry_time":720,"ferry_price":778,"cargo":"cargo.olive_oil","company_truck":"scania_streamline_4x2_b","trailer_variant":"trailer.scs_curt","trailer_definition":"trailer_def.scs.box.single_3.curtain","units_count":33,"fill_ratio":1,"trailer_place":0},{"target":"cargotras.livorno","urgency":1,"shortest_distance_km":1181,"ferry_time":20,"ferry_price":347,"cargo":"cargo.moto_tires","company_truck":"scania_r_4x2_370","trailer_variant":"trailer.scs_dry","trailer_definition":"trailer_def.scs.box.single_3.dryvan","units_count":33,"fill_ratio":1,"trailer_place":0}],"eolo_lines.napoli":[{"target":"tras_med.cagliari","urgency":1,"shortest_distance_km":38,"ferry_time":840,"ferry_price":879,"cargo":"cargo.moto_tires","company_truck":"scania_6x2_b","trailer_variant":"trailer.scs_dry_m","trailer_definition":"trailer_def.scs.box.single_3.dryvan_m","units_count":33,"fill_ratio":1,"trailer_place":0},{"target":"te_logistica.sassari","urgency":0,"shortest_distance_km":215,"ferry_time":840,"ferry_price":879,"cargo":"cargo.nuts","company_truck":"man_4x2_a","trailer_variant":"trailer.scs_dry_a","trailer_definition":"trailer_def.scs.box.single_3.dryvan","units_count":33,"fill_ratio":1,"trailer_place":0}],"quadrelli.pescara":[{"target":"fui.roma","urgency":2,"shortest_distance_km":340,"ferry_time":0,"ferry_price":0,"cargo":"cargo.excav_soil","company_truck":"daf_4x2_a","trailer_variant":"trailer.s_ki_solid.cover","trailer_definition":"trailer_def.excav_soil.s_ki_solid.cover","units_count":100,"fill_ratio":1,"trailer_place":0}],"cargotras.olbia":[{"target":"cesare_smar.pescara","urgency":1,"shortest_distance_km":544,"ferry_time":840,"ferry_price":879,"cargo":"cargo.apples","company_truck":"mercedes_4x2","trailer_variant":"trailer.scs_dry_m","trailer_definition":"trailer_def.scs.box.single_3.dryvan_m","units_count":33,"fill_ratio":1,"trailer_place":0}],"tras_med.roma":[{"target":"te_logistica.firenze","urgency":2,"shortest_distance_km":305,"ferry_time":0,"ferry_price":0,"cargo":"cargo.used_packag","company_truck":"mercedes_6x4_a","trailer_variant":"trailer.scs_curt_a","trailer_definition":"trailer_def.scs.box.single_3.curtain","units_count":33,"fill_ratio":1,"trailer_place":0},{"target":"exomar.roma","urgency":2,"shortest_distance_km":1,"ferry_time":0,"ferry_price":0,"cargo":"cargo.almond","company_truck":"mercedes_4x2_a","trailer_variant":"trailer.scs_dry_ms","trailer_definition":"trailer_def.scs.box.single_3.dryvan_m","units_count":33,"fill_ratio":1,"trailer_place":0}],"piac.napoli":[{"target":"te_logistica.firenze","urgency":1,"shortest_distance_km":524,"ferry_time":0,"ferry_price":0,"cargo":"cargo.empty_palet","company_truck":"scania_6x4_a","trailer_variant":"trailer.scs_dry_m","trailer_definition":"trailer_def.scs.box.single_3.dryvan_m","units_count":33,"fill_ratio":1,"trailer_place":0},{"target":"tras_med.cagliari","urgency":1,"shortest_distance_km":43,"ferry_time":840,"ferry_price":879,"cargo":"cargo.used_battery","company_truck":"mercedes_4x2_c","trailer_variant":"trailer.scs_dry_s","trailer_definition":"trailer_def.scs.box.single_3.dryvan","units_count":33,"fill_ratio":1,"trailer_place":0}],"cargotras.catanzaro":[{"target":"pp_chimica.terni","urgency":1,"shortest_distance_km":629,"ferry_time":0,"ferry_price":0,"cargo":"cargo.coal","company_truck":"mercedes_actros_2014_4x2_b","trailer_variant":"trailer.s_ki_solid.coal","trailer_definition":"trailer_def.coal.s_ki_solid.coal","units_count":100,"fill_ratio":1,"trailer_place":0},{"target":"ika_bohag.roma","urgency":1,"shortest_distance_km":564,"ferry_time":0,"ferry_price":0,"cargo":"cargo.tableware","company_truck":"man_tgx_euro6_4x2_xxl","trailer_variant":"trailer.scs_curt_s","trailer_definition":"trailer_def.scs.box.single_3.curtain","units_count":33,"fill_ratio":1,"trailer_place":0}],"c_navale.messina":[{"target":"tras_med.catania","urgency":1,"shortest_distance_km":141,"ferry_time":0,"ferry_price":0,"cargo":"cargo.empty_palet","company_truck":"scania_streamline_4x2_b","trailer_variant":"trailer.scs_dry_a","trailer_definition":"trailer_def.scs.box.single_3.dryvan","units_count":33,"fill_ratio":1,"trailer_place":0}],"exomar.taranto":[{"target":"tras_med.bari","urgency":1,"shortest_distance_km":85,"ferry_time":0,"ferry_price":0,"cargo":"cargo.chocolate","company_truck":"renault_t_4x2h","trailer_variant":"trailer.scs_curt","trailer_definition":"trailer_def.scs.box.single_3.curtain","units_count":33,"fill_ratio":1,"trailer_place":0}],"piac.bologna":[{"target":"cargotras.pescara","urgency":2,"shortest_distance_km":427,"ferry_time":0,"ferry_price":0,"cargo":"cargo.used_packag","company_truck":"mercedes_4x2_a","trailer_variant":"trailer.scs_dry","trailer_definition":"trailer_def.scs.box.single_3.dryvan","units_count":33,"fill_ratio":1,"trailer_place":0}],"fui.olbia":[{"target":"cont_port_it.bari","urgency":2,"shortest_distance_km":446,"ferry_time":840,"ferry_price":879,"cargo":"cargo.carrots_c","company_truck":"renault_magnum_6x2_a","trailer_variant":"trailer.scs_flat_c_g","trailer_definition":"trailer_def.scs.flatbed.single_3.container","units_count":33,"fill_ratio":1,"trailer_place":0}],"cnp.taranto":[{"target":"acc.taranto","urgency":0,"shortest_distance_km":9,"ferry_time":0,"ferry_price":0,"cargo":"cargo.lpg","company_truck":"renault_t_6x2","trailer_variant":"trailer.willig.fuel_cistern","trailer_definition":"trailer_def.lpg.willig.fuel_cistern","units_count":101,"fill_ratio":1,"trailer_place":0},{"target":"cont_port_it.livorno","urgency":0,"shortest_distance_km":793,"ferry_time":0,"ferry_price":0,"cargo":"cargo.carbn_pwdr_c","company_truck":"scania_streamline_4x2_a","trailer_variant":"trailer.scs_gosck20","trailer_definition":"trailer_def.scs.gooseneck.singl_3e_20.container","units_count":15,"fill_ratio":1,"trailer_place":0}],"libellula.bologna":[{"target":"tras_med.cagliari","urgency":2,"shortest_distance_km":677,"ferry_time":840,"ferry_price":879,"cargo":"cargo.scrap_metals","company_truck":"scania_6x2_b","trailer_variant":"trailer.s_ki_solid.cover","trailer_definition":"trailer_def.scrap_metals.s_ki_solid.cover","units_count":100,"fill_ratio":1,"trailer_place":0},{"target":"cargotras.livorno","urgency":2,"shortest_distance_km":189,"ferry_time":0,"ferry_price":0,"cargo":"cargo.scooters","company_truck":"mercedes_actros_2014_4x2_a","trailer_variant":"trailer.scs_dry_ms","trailer_definition":"trailer_def.scs.box.single_3.dryvan_m","units_count":33,"fill_ratio":1,"trailer_place":0}],"comoto.suzzara":[{"target":"cnp.taranto","urgency":1,"shortest_distance_km":800,"ferry_time":0,"ferry_price":0,"cargo":"cargo.empty_palet","company_truck":"mercedes_actros_2014_4x2_a","trailer_variant":"trailer.scs_dry_s","trailer_definition":"trailer_def.scs.box.single_3.dryvan","units_count":33,"fill_ratio":1,"trailer_place":0}],"tradeaux.geneve":[{"target":"lkwlog.hamburg","urgency":1,"shortest_distance_km":1022,"ferry_time":0,"ferry_price":0,"cargo":"cargo.metal_pipes","company_truck":"mercedes_actros_2014_4x2_a","trailer_variant":"trailer.scs_flat_c_r","trailer_definition":"trailer_def.scs.flatbed.single_3.container","units_count":1,"fill_ratio":1,"trailer_place":0}],"ika_bohag.firenze":[{"target":"exomar.taranto","urgency":2,"shortest_distance_km":845,"ferry_time":0,"ferry_price":0,"cargo":"cargo.used_packag","company_truck":"man_6x4_b","trailer_variant":"trailer.scs_dry_ms","trailer_definition":"trailer_def.scs.box.single_3.dryvan_m","units_count":33,"fill_ratio":1,"trailer_place":0}],"aaa.roma":[{"target":"cargotras.pescara","urgency":0,"shortest_distance_km":223,"ferry_time":0,"ferry_price":0,"cargo":"cargo.car_it","company_truck":"daf_xf_euro6_6x4_c","trailer_variant":"trailer.car_it","trailer_definition":"trailer_def.car_it.car_it","units_count":100,"fill_ratio":1,"trailer_place":0}],"fattoria_f.roma":[{"target":"te_logistica.cagliari","urgency":1,"shortest_distance_km":217,"ferry_time":840,"ferry_price":879,"cargo":"cargo.milk","company_truck":"iveco_h_4x2_a","trailer_variant":"trailer.scs_dry_a","trailer_definition":"trailer_def.scs.box.single_3.dryvan","units_count":33,"fill_ratio":1,"trailer_place":0}],"eolo_lines.sassari":[{"target":"ika_bohag.napoli","urgency":1,"shortest_distance_km":253,"ferry_time":840,"ferry_price":879,"cargo":"cargo.clothes_c","company_truck":"renault_t_4x2h","trailer_variant":"trailer.scs_flat_c_g","trailer_definition":"trailer_def.scs.flatbed.single_3.container","units_count":33,"fill_ratio":1,"trailer_place":0}],"te_logistica.messina":[{"target":"cargotras.livorno","urgency":1,"shortest_distance_km":977,"ferry_time":20,"ferry_price":347,"cargo":"cargo.flour","company_truck":"scania_s_4x2_370","trailer_variant":"trailer.scs_dry_s","trailer_definition":"trailer_def.scs.box.single_3.dryvan","units_count":33,"fill_ratio":1,"trailer_place":0},{"target":"costruzi_fla.catanzaro","urgency":1,"shortest_distance_km":165,"ferry_time":20,"ferry_price":347,"cargo":"cargo.metal_pipes","company_truck":"scania_6x4_a","trailer_variant":"trailer.scs_flat_c_g","trailer_definition":"trailer_def.scs.flatbed.single_3.container","units_count":2,"fill_ratio":1,"trailer_place":0},{"target":"exomar.taranto","urgency":0,"shortest_distance_km":416,"ferry_time":20,"ferry_price":347,"cargo":"cargo.pesto","company_truck":"scania_streamline_6x4_a","trailer_variant":"trailer.scs_dry_ms","trailer_definition":"trailer_def.scs.box.single_3.dryvan_m","units_count":33,"fill_ratio":1,"trailer_place":0}],"kaarfor.edinburgh":[{"target":"tras_med.catania","urgency":2,"shortest_distance_km":3204,"ferry_time":55,"ferry_price":647,"cargo":"cargo.used_packag","company_truck":"scania_streamline_4x2_c","trailer_variant":"trailer.scs_curt_s","trailer_definition":"trailer_def.scs.box.single_3.curtain","units_count":33,"fill_ratio":1,"trailer_place":0}],"cnp.ancona":[{"target":"piac.bologna","urgency":1,"shortest_distance_km":241,"ferry_time":0,"ferry_price":0,"cargo":"cargo.motor_oil_c","company_truck":"iveco_6x2_a","trailer_variant":"trailer.scs_gosck40","trailer_definition":"trailer_def.scs.gooseneck.singl_3e_40.container","units_count":30,"fill_ratio":1,"trailer_place":0},{"target":"sal.terni","urgency":0,"shortest_distance_km":221,"ferry_time":0,"ferry_price":0,"cargo":"cargo.lpg","company_truck":"scania_6x4_a","trailer_variant":"trailer.willig.fuel_cistern","trailer_definition":"trailer_def.lpg.willig.fuel_cistern","units_count":101,"fill_ratio":1,"trailer_place":0}],"itcc.glasgow":[{"target":"sanbuilders.london","urgency":0,"shortest_distance_km":675,"ferry_time":0,"ferry_price":0,"cargo":"cargo.sq_tub","company_truck":"scania_6x2_b","trailer_variant":"trailer.scs_flat_r","trailer_definition":"trailer_def.scs.flatbed.single_3.flatbed_w","units_count":2,"fill_ratio":1,"trailer_place":0}],"tras_med.genova":[{"target":"ini.suzzara","urgency":1,"shortest_distance_km":355,"ferry_time":0,"ferry_price":0,"cargo":"cargo.petrol","company_truck":"renault_magnum_6x2_a","trailer_variant":"trailer.fuel_cistern","trailer_definition":"trailer_def.petrol.fuel_cistern","units_count":100,"fill_ratio":1,"trailer_place":0}],"eolo_lines.cagliari":[{"target":"exomar.olbia","urgency":1,"shortest_distance_km":253,"ferry_time":0,"ferry_price":0,"cargo":"cargo.clothes_c","company_truck":"scania_r_6x2_450","trailer_variant":"trailer.scs_flat_c_r","trailer_definition":"trailer_def.scs.flatbed.single_3.container","units_count":33,"fill_ratio":1,"trailer_place":0}],"cnp.livorno":[{"target":"sal.sassari","urgency":0,"shortest_distance_km":722,"ferry_time":840,"ferry_price":879,"cargo":"cargo.oil","company_truck":"scania_r_4x2_370","trailer_variant":"trailer.fuel_cistern","trailer_definition":"trailer_def.oil.fuel_cistern","units_count":100,"fill_ratio":1,"trailer_place":0},{"target":"pp_chimica.terni","urgency":1,"shortest_distance_km":302,"ferry_time":0,"ferry_price":0,"cargo":"cargo.motor_oil_c","company_truck":"renault_t_4x2","trailer_variant":"trailer.scs_flat_c_g","trailer_definition":"trailer_def.scs.flatbed.single_3.container","units_count":33,"fill_ratio":1,"trailer_place":0}],"cont_port_it.genova":[{"target":"cargotras.catanzaro","urgency":2,"shortest_distance_km":1104,"ferry_time":0,"ferry_price":0,"cargo":"cargo.carrots_c","company_truck":"man_4x2_c","trailer_variant":"trailer.scs_flat_c_r","trailer_definition":"trailer_def.scs.flatbed.single_3.container","units_count":33,"fill_ratio":1,"trailer_place":0},{"target":"te_logistica.firenze","urgency":0,"shortest_distance_km":275,"ferry_time":0,"ferry_price":0,"cargo":"cargo.chem_sorb_c","company_truck":"mercedes_4x2","trailer_variant":"trailer.scs_flat_c_r","trailer_definition":"trailer_def.scs.flatbed.single_3.container","units_count":33,"fill_ratio":1,"trailer_place":0}],"piac.parma":[{"target":"tras_med.bari","urgency":1,"shortest_distance_km":817,"ferry_time":0,"ferry_price":0,"cargo":"cargo.used_battery","company_truck":"mercedes_actros_2014_4x2_b","trailer_variant":"trailer.scs_dry_ms","trailer_definition":"trailer_def.scs.box.single_3.dryvan_m","units_count":33,"fill_ratio":1,"trailer_place":0},{"target":"cargotras.livorno","urgency":1,"shortest_distance_km":275,"ferry_time":0,"ferry_price":0,"cargo":"cargo.empty_palet","company_truck":"man_tgx_euro6_4x2_xl","trailer_variant":"trailer.scs_dry_a","trailer_definition":"trailer_def.scs.box.single_3.dryvan","units_count":33,"fill_ratio":1,"trailer_place":0}],"tesore_gust.parma":[{"target":"tras_med.genova","urgency":2,"shortest_distance_km":260,"ferry_time":0,"ferry_price":0,"cargo":"cargo.limonades","company_truck":"man_4x2_a","trailer_variant":"trailer.scs_dry","trailer_definition":"trailer_def.scs.box.single_3.dryvan","units_count":33,"fill_ratio":1,"trailer_place":0},{"target":"eolo_lines.sangiovanni","urgency":2,"shortest_distance_km":1092,"ferry_time":0,"ferry_price":0,"cargo":"cargo.prosciutto","company_truck":"iveco_4x2_b","trailer_variant":"trailer.scs_ref","trailer_definition":"trailer_def.scs.box.single_3.reefer","units_count":33,"fill_ratio":1,"trailer_place":0}],"fui.catania":[{"target":"cesare_smar.palermo","urgency":0,"shortest_distance_km":166,"ferry_time":0,"ferry_price":0,"cargo":"cargo.tomatoes","company_truck":"scania_s_6x4_730","trailer_variant":"trailer.scs_ins_a","trailer_definition":"trailer_def.scs.box.single_3.insulated","units_count":33,"fill_ratio":1,"trailer_place":0}],"eolo_lines.messina":[{"target":"te_logistica.cagliari","urgency":0,"shortest_distance_km":223,"ferry_time":720,"ferry_price":778,"cargo":"cargo.potatoes","company_truck":"mercedes_actros_2014_6x4_b","trailer_variant":"trailer.scs_curt","trailer_definition":"trailer_def.scs.box.single_3.curtain","units_count":33,"fill_ratio":1,"trailer_place":0}],"sellplan.torino":[{"target":"cargotras.olbia","urgency":2,"shortest_distance_km":694,"ferry_time":1050,"ferry_price":1548,"cargo":"cargo.used_packag","company_truck":"renault_magnum_6x4_a","trailer_variant":"trailer.scs_dry_ms","trailer_definition":"trailer_def.scs.box.single_3.dryvan_m","units_count":33,"fill_ratio":1,"trailer_place":0}],"cargotras.palermo":[{"target":"te_logistica.messina","urgency":1,"shortest_distance_km":206,"ferry_time":0,"ferry_price":0,"cargo":"cargo.maple_syrup","company_truck":"scania_6x4_a","trailer_variant":"trailer.scs_curt_a","trailer_definition":"trailer_def.scs.box.single_3.curtain","units_count":33,"fill_ratio":1,"trailer_place":0},{"target":"acc.taranto","urgency":0,"shortest_distance_km":563,"ferry_time":20,"ferry_price":347,"cargo":"cargo.carbn_pwdr_c","company_truck":"scania_r_6x4_650","trailer_variant":"trailer.scs_gosck40","trailer_definition":"trailer_def.scs.gooseneck.singl_3e_40.container","units_count":30,"fill_ratio":1,"trailer_place":0}],"te_logistica.sassari":[{"target":"marmo.palermo","urgency":1,"shortest_distance_km":285,"ferry_time":720,"ferry_price":778,"cargo":"cargo.excavator","company_truck":"renault_t_4x2","trailer_variant":"trailer.scs_lowbed_3","trailer_definition":"trailer_def.scs.lowbed.single_3.short","units_count":1,"fill_ratio":1,"trailer_place":0}],"cesare_smar.pescara":[{"target":"tesore_gust.firenze","urgency":1,"shortest_distance_km":412,"ferry_time":0,"ferry_price":0,"cargo":"cargo.empty_palet","company_truck":"man_6x4_b","trailer_variant":"trailer.scs_dry_a","trailer_definition":"trailer_def.scs.box.single_3.dryvan","units_count":33,"fill_ratio":1,"trailer_place":0},{"target":"exomar.ancona","urgency":1,"shortest_distance_km":182,"ferry_time":0,"ferry_price":0,"cargo":"cargo.used_plast","company_truck":"scania_s_4x2_580","trailer_variant":"trailer.scs_curt_a","trailer_definition":"trailer_def.scs.box.single_3.curtain","units_count":33,"fill_ratio":1,"trailer_place":0}],"spinelli.milano":[{"target":"tras_med.roma","urgency":1,"shortest_distance_km":627,"ferry_time":0,"ferry_price":0,"cargo":"cargo.moto_tires","company_truck":"renault_t_6x2","trailer_variant":"trailer.scs_dry_m","trailer_definition":"trailer_def.scs.box.single_3.dryvan_m","units_count":33,"fill_ratio":1,"trailer_place":0}],"quadrelli.catania":[{"target":"costruzi_fla.catanzaro","urgency":1,"shortest_distance_km":346,"ferry_time":20,"ferry_price":347,"cargo":"cargo.marb_blck","company_truck":"mercedes_actros_2014_6x2_a","trailer_variant":"trailer.scs_flat_b","trailer_definition":"trailer_def.scs.flatbed.single_3.flatbed_w","units_count":2,"fill_ratio":1,"trailer_place":0}],"eolo_lines.sangiovanni":[{"target":"cargotras.catanzaro","urgency":2,"shortest_distance_km":160,"ferry_time":0,"ferry_price":0,"cargo":"cargo.olive_oil","company_truck":"scania_streamline_4x2_b","trailer_variant":"trailer.scs_dry","trailer_definition":"trailer_def.scs.box.single_3.dryvan","units_count":33,"fill_ratio":1,"trailer_place":0}],"exomar.olbia":[{"target":"cargotras.pescara","urgency":0,"shortest_distance_km":544,"ferry_time":840,"ferry_price":879,"cargo":"cargo.oil_filt_c","company_truck":"scania_4x2_c","trailer_variant":"trailer.scs_gosck220","trailer_definition":"trailer_def.scs.gooseneck.singl_3e_220.container","units_count":30,"fill_ratio":1,"trailer_place":0}],"bcp.verona":[{"target":"te_logistica.cagliari","urgency":1,"shortest_distance_km":777,"ferry_time":840,"ferry_price":879,"cargo":"cargo.used_battery","company_truck":"mercedes_actros_2014_4x2_b","trailer_variant":"trailer.scs_curt_s","trailer_definition":"trailer_def.scs.box.single_3.curtain","units_count":33,"fill_ratio":1,"trailer_place":0}],"kaarfor.cambridge":[{"target":"tesore_gust.parma","urgency":1,"shortest_distance_km":1429,"ferry_time":35,"ferry_price":300,"cargo":"cargo.empty_palet","company_truck":"mercedes_actros_2014_6x4_b","trailer_variant":"trailer.scs_curt_s","trailer_definition":"trailer_def.scs.box.single_3.curtain","units_count":33,"fill_ratio":1,"trailer_place":0}],"cesare_smar.palermo":[{"target":"cargotras.catanzaro","urgency":1,"shortest_distance_km":367,"ferry_time":20,"ferry_price":347,"cargo":"cargo.used_plast","company_truck":"mercedes_4x2","trailer_variant":"trailer.scs_curt_a","trailer_definition":"trailer_def.scs.box.single_3.curtain","units_count":33,"fill_ratio":1,"trailer_place":0},{"target":"te_logistica.messina","urgency":2,"shortest_distance_km":206,"ferry_time":0,"ferry_price":0,"cargo":"cargo.used_packag","company_truck":"renault_magnum_6x4_a","trailer_variant":"trailer.scs_curt_a","trailer_definition":"trailer_def.scs.box.single_3.curtain","units_count":33,"fill_ratio":1,"trailer_place":0}],"aci.bologna":[{"target":"te_logistica.parma","urgency":2,"shortest_distance_km":118,"ferry_time":0,"ferry_price":0,"cargo":"cargo.med_equip","company_truck":"iveco_h_4x2_a","trailer_variant":"trailer.scs_dry_s","trailer_definition":"trailer_def.scs.box.single_3.dryvan","units_count":33,"fill_ratio":1,"trailer_place":0}],"cont_port_it.ancona":[{"target":"acc.terni","urgency":0,"shortest_distance_km":179,"ferry_time":0,"ferry_price":0,"cargo":"cargo.carbn_pwdr_c","company_truck":"iveco_h_4x2_a","trailer_variant":"trailer.scs_gosck40","trailer_definition":"trailer_def.scs.gooseneck.singl_3e_40.container","units_count":30,"fill_ratio":1,"trailer_place":0}]}