{"fle.paris":[{"target":"balkan_loco.craiova","urgency":0,"shortest_distance_km":2105,"ferry_time":0,"ferry_price":0,"cargo":"cargo.med_equip","company_truck":"man_4x2_a","trailer_variant":"trailer.scs_dry_ms","trailer_definition":"trailer_def.scs.box.single_3.dryvan_m","units_count":33,"fill_ratio":1,"trailer_place":0}],"tree_et.dortmund":[{"target":"fallow.cluj_napoca","urgency":1,"shortest_distance_km":1738,"ferry_time":0,"ferry_price":0,"cargo":"cargo.forklifts","company_truck":"man_6x4_b","trailer_variant":"trailer.scs_lowbed_3","trailer_definition":"trailer_def.scs.lowbed.single_3.short","units_count":1,"fill_ratio":1,"trailer_place":0}],"wgcc.bratislava":[{"target":"lognstick.tekirdag","urgency":1,"shortest_distance_km":1593,"ferry_time":0,"ferry_price":0,"cargo":"cargo.hipresstank","company_truck":"mercedes_6x4_a","trailer_variant":"trailer.scs_flat_c_r","trailer_definition":"trailer_def.scs.flatbed.single_3.container","units_count":2,"fill_ratio":1,"trailer_place":0}],"fcp.brussel":[{"target":"baltrak.istanbul","urgency":2,"shortest_distance_km":2800,"ferry_time":0,"ferry_price":0,"cargo":"cargo.used_battery","company_truck":"daf_4x2_b","trailer_variant":"trailer.scs_dry_ms","trailer_definition":"trailer_def.scs.box.single_3.dryvan_m","units_count":33,"fill_ratio":1,"trailer_place":0}],"tree_et.innsbruck":[{"target":"ns_oil.brasov","urgency":2,"shortest_distance_km":1528,"ferry_time":0,"ferry_price":0,"cargo":"cargo.empty_palet","company_truck":"renault_premium_4x2_c","trailer_variant":"trailer.scs_curt_s","trailer_definition":"trailer_def.scs.box.single_3.curtain","units_count":33,"fill_ratio":1,"trailer_place":0}],"lkwlog.luxembourg":[{"target":"baltrak.istanbul","urgency":0,"shortest_distance_km":2578,"ferry_time":0,"ferry_price":0,"cargo":"cargo.cauliflower","company_truck":"daf_xf_euro6_4x2_b","trailer_variant":"trailer.scs_ref_s","trailer_definition":"trailer_def.scs.box.single_3.reefer","units_count":33,"fill_ratio":1,"trailer_place":0}],"tradeaux.rostock":[{"target":"ttk_bg.plovdiv","urgency":2,"shortest_distance_km":2187,"ferry_time":0,"ferry_price":0,"cargo":"cargo.beverages_c","company_truck":"mercedes_4x2_b","trailer_variant":"trailer.scs_flat_c_r","trailer_definition":"trailer_def.scs.flatbed.single_3.container","units_count":33,"fill_ratio":1,"trailer_place":0}],"tree_et.bratislava":[{"target":"lognstick.galati","urgency":2,"shortest_distance_km":1315,"ferry_time":0,"ferry_price":0,"cargo":"cargo.digger500","company_truck":"daf_xf_euro6_4x2_c","trailer_variant":"trailer.scs_lowbed_3","trailer_definition":"trailer_def.scs.lowbed.single_3.short","units_count":1,"fill_ratio":1,"trailer_place":0}],"sellplan.sheffield":[{"target":"fallow.cluj_napoca","urgency":1,"shortest_distance_km":2617,"ferry_time":35,"ferry_price":300,"cargo":"cargo.used_plast_c","company_truck":"scania_streamline_6x4_a","trailer_variant":"trailer.scs_flat_c_r","trailer_definition":"trailer_def.scs.flatbed.single_3.container","units_count":33,"fill_ratio":1,"trailer_place":0}],"tradeaux.lyon":[{"target":"domdepo.edirne","urgency":0,"shortest_distance_km":2609,"ferry_time":0,"ferry_price":0,"cargo":"cargo.rooflights","company_truck":"man_tgx_euro6_6x4_xlx","trailer_variant":"trailer.scs_dry_ms","trailer_definition":"trailer_def.scs.box.single_3.dryvan_m","units_count":33,"fill_ratio":1,"trailer_place":0}],"lkwlog.amsterdam":[{"target":"balkan_loco.veli_tarnovo","urgency":0,"shortest_distance_km":2360,"ferry_time":0,"ferry_price":0,"cargo":"cargo.apples","company_truck":"daf_xf_euro6_6x2_a","trailer_variant":"trailer.scs_dry_m","trailer_definition":"trailer_def.scs.box.single_3.dryvan_m","units_count":33,"fill_ratio":1,"trailer_place":0}],"quarry.salzburg":[{"target":"fallow.timisoara","urgency":1,"shortest_distance_km":928,"ferry_time":0,"ferry_price":0,"cargo":"cargo.fueltanker","company_truck":"iveco_4x2_b","trailer_variant":"trailer.scs_flat_c_r","trailer_definition":"trailer_def.scs.flatbed.single_3.container","units_count":87,"fill_ratio":1,"trailer_place":0}],"trameri.klagenfurt":[{"target":"fallow.cluj_napoca","urgency":1,"shortest_distance_km":944,"ferry_time":0,"ferry_price":0,"cargo":"cargo.fueltanker","company_truck":"scania_s_6x2_450","trailer_variant":"trailer.scs_gosck40","trailer_definition":"trailer_def.scs.gooseneck.singl_3e_40.container","units_count":80,"fill_ratio":1,"trailer_place":0}],"sellplan.london":[{"target":"baltrak.istanbul","urgency":1,"shortest_distance_km":3104,"ferry_time":35,"ferry_price":300,"cargo":"cargo.used_packag","company_truck":"man_tgx_euro6_6x4_xlx","trailer_variant":"trailer.scs_dry_s","trailer_definition":"trailer_def.scs.box.single_3.dryvan","units_count":33,"fill_ratio":1,"trailer_place":0}],"sanbuilders.birmingham":[{"target":"imp_otel.galati","urgency":1,"shortest_distance_km":2942,"ferry_time":35,"ferry_price":300,"cargo":"cargo.forklifts","company_truck":"renault_magnum_4x2_a","trailer_variant":"trailer.scs_lowbed_4","trailer_definition":"trailer_def.scs.lowbed.single_4_sh.short","units_count":1,"fill_ratio":1,"trailer_place":0}],"stokes.nurnberg":[{"target":"kaarfor.constanta","urgency":0,"shortest_distance_km":1789,"ferry_time":0,"ferry_price":0,"cargo":"cargo.beverages","company_truck":"scania_streamline_4x2_b","trailer_variant":"trailer.scs_curt","trailer_definition":"trailer_def.scs.box.single_3.curtain","units_count":33,"fill_ratio":1,"trailer_place":0}],"kaarfor.reims":[{"target":"lognstick.hunedoara","urgency":1,"shortest_distance_km":1799,"ferry_time":0,"ferry_price":0,"cargo":"cargo.used_plast_c","company_truck":"iveco_4x2_a","trailer_variant":"trailer.scs_gosck20","trailer_definition":"trailer_def.scs.gooseneck.singl_3e_20.container","units_count":15,"fill_ratio":1,"trailer_place":0}],"sellplan.venezia":[{"target":"ttk_bg.plovdiv","urgency":2,"shortest_distance_km":1844,"ferry_time":0,"ferry_price":0,"cargo":"cargo.empty_palet","company_truck":"scania_r_6x4_650","trailer_variant":"trailer.scs_dry_ms","trailer_definition":"trailer_def.scs.box.single_3.dryvan_m","units_count":32,"fill_ratio":1,"trailer_place":0}],"lisette_log.paris":[{"target":"ocean_sol.ruse","urgency":1,"shortest_distance_km":2473,"ferry_time":0,"ferry_price":0,"cargo":"cargo.oil_filt_c","company_truck":"man_6x4_b","trailer_variant":"trailer.scs_flat_c_g","trailer_definition":"trailer_def.scs.flatbed.single_3.container","units_count":33,"fill_ratio":1,"trailer_place":0}],"fallow.timisoara":[{"target":"eurogoodies.innsbruck","urgency":0,"shortest_distance_km":1051,"ferry_time":0,"ferry_price":0,"cargo":"cargo.vinegar","company_truck":"scania_streamline_4x2_c","trailer_variant":"trailer.scs_dry_a","trailer_definition":"trailer_def.scs.box.single_3.dryvan","units_count":33,"fill_ratio":1,"trailer_place":0}],"trainfoundry.karlovo":[{"target":"lkwlog.brno","urgency":1,"shortest_distance_km":1375,"ferry_time":0,"ferry_price":0,"cargo":"cargo.scrap_metals","company_truck":"daf_6x2_a","trailer_variant":"trailer.s_ki_solid.cover","trailer_definition":"trailer_def.scrap_metals.s_ki_solid.cover","units_count":100,"fill_ratio":1,"trailer_place":0}],"ttk_bg.plovdiv":[{"target":"stokes.aberdeen","urgency":1,"shortest_distance_km":3738,"ferry_time":35,"ferry_price":300,"cargo":"cargo.canned_beans","company_truck":"mercedes_actros_2014_6x4_b","trailer_variant":"trailer.scs_dry_s","trailer_definition":"trailer_def.scs.box.single_3.dryvan","units_count":33,"fill_ratio":1,"trailer_place":0},{"target":"kaarfor.reims","urgency":1,"shortest_distance_km":2462,"ferry_time":0,"ferry_price":0,"cargo":"cargo.almond","company_truck":"man_6x4_b","trailer_variant":"trailer.scs_dry_ms","trailer_definition":"trailer_def.scs.box.single_3.dryvan_m","units_count":33,"fill_ratio":1,"trailer_place":0}],"kaarfor.constanta":[{"target":"lkwlog.brno","urgency":1,"shortest_distance_km":1357,"ferry_time":0,"ferry_price":0,"cargo":"cargo.used_plast_c","company_truck":"scania_4x2_c","trailer_variant":"trailer.scs_flat_c_r","trailer_definition":"trailer_def.scs.flatbed.single_3.container","units_count":33,"fill_ratio":1,"trailer_place":0}],"radus_ru.ruse":[{"target":"stokes.kiel","urgency":0,"shortest_distance_km":2053,"ferry_time":0,"ferry_price":0,"cargo":"cargo.emptytank","company_truck":"daf_xf_euro6_4x2_a","trailer_variant":"trailer.scs_flat_c_g","trailer_definition":"trailer_def.scs.flatbed.single_3.container","units_count":2,"fill_ratio":1,"trailer_place":0}],"renat.resita":[{"target":"kaarfor.munchen","urgency":2,"shortest_distance_km":1087,"ferry_time":0,"ferry_price":0,"cargo":"cargo.furniture","company_truck":"scania_4x2_a","trailer_variant":"trailer.scs_dry_m","trailer_definition":"trailer_def.scs.box.single_3.dryvan_m","units_count":33,"fill_ratio":1,"trailer_place":0}],"ika_bohag.bucuresti":[{"target":"lkwlog.calais","urgency":1,"shortest_distance_km":2399,"ferry_time":0,"ferry_price":0,"cargo":"cargo.used_packag","company_truck":"scania_s_4x2_370","trailer_variant":"trailer.scs_curt_s","trailer_definition":"trailer_def.scs.box.single_3.curtain","units_count":33,"fill_ratio":1,"trailer_place":0}],"ns_oil.timisoara":[{"target":"posped.bratislava","urgency":1,"shortest_distance_km":524,"ferry_time":0,"ferry_price":0,"cargo":"cargo.oil","company_truck":"renault_magnum_6x2_a","trailer_variant":"trailer.fuel_cistern","trailer_definition":"trailer_def.oil.fuel_cistern","units_count":100,"fill_ratio":1,"trailer_place":0},{"target":"tradeaux.lyon","urgency":2,"shortest_distance_km":1659,"ferry_time":0,"ferry_price":0,"cargo":"cargo.petrol","company_truck":"mercedes_actros_2014_4x2_a","trailer_variant":"trailer.willig.fuel_cistern","trailer_definition":"trailer_def.petrol.willig.fuel_cistern","units_count":101,"fill_ratio":1,"trailer_place":0}],"lognstick.tekirdag":[{"target":"transinet.salzburg","urgency":0,"shortest_distance_km":1913,"ferry_time":0,"ferry_price":0,"cargo":"cargo.chocolate","company_truck":"man_4x2_c","trailer_variant":"trailer.scs_dry_s","trailer_definition":"trailer_def.scs.box.single_3.dryvan","units_count":30,"fill_ratio":1,"trailer_place":0}],"sporklift.cluj_napoca":[{"target":"cargotras.milano","urgency":1,"shortest_distance_km":1459,"ferry_time":0,"ferry_price":0,"cargo":"cargo.used_plast_c","company_truck":"scania_streamline_4x2_c","trailer_variant":"trailer.scs_flat_c_g","trailer_definition":"trailer_def.scs.flatbed.single_3.container","units_count":33,"fill_ratio":1,"trailer_place":0},{"target":"lkwlog.brno","urgency":1,"shortest_distance_km":829,"ferry_time":0,"ferry_price":0,"cargo":"cargo.forklifts","company_truck":"man_6x4_b","trailer_variant":"trailer.scs_lowbed_3","trailer_definition":"trailer_def.scs.lowbed.single_3.short","units_count":1,"fill_ratio":1,"trailer_place":0}],"ns_oil.brasov":[{"target":"fcp.poznan","urgency":1,"shortest_distance_km":1413,"ferry_time":0,"ferry_price":0,"cargo":"cargo.oil","company_truck":"scania_streamline_4x2_c","trailer_variant":"trailer.fuel_cistern","trailer_definition":"trailer_def.oil.fuel_cistern","units_count":100,"fill_ratio":1,"trailer_place":0}],"cgla.calarasi":[{"target":"posped.graz","urgency":0,"shortest_distance_km":1216,"ferry_time":0,"ferry_price":0,"cargo":"cargo.glass","company_truck":"renault_t_4x2","trailer_variant":"trailer.panel_trans.glass","trailer_definition":"trailer_def.glass.panel_trans.glass","units_count":90,"fill_ratio":1,"trailer_place":0}],"fle.cluj_napoca":[{"target":"stokes.wien","urgency":0,"shortest_distance_km":804,"ferry_time":0,"ferry_price":0,"cargo":"cargo.med_equip","company_truck":"daf_xf_euro6_6x4_c","trailer_variant":"trailer.scs_dry_a","trailer_definition":"trailer_def.scs.box.single_3.dryvan","units_count":33,"fill_ratio":1,"trailer_place":0}],"kolico.timisoara":[{"target":"transinet.hamburg","urgency":0,"shortest_distance_km":1466,"ferry_time":0,"ferry_price":0,"cargo":"cargo.beverages","company_truck":"man_tgx_euro6_4x2_xxl","trailer_variant":"trailer.scs_ref_s","trailer_definition":"trailer_def.scs.box.single_3.reefer","units_count":30,"fill_ratio":1,"trailer_place":0}],"rock_eater.constanta":[{"target":"transinet.cambridge","urgency":0,"shortest_distance_km":2889,"ferry_time":35,"ferry_price":300,"cargo":"cargo.digger1000","company_truck":"daf_xf_euro6_4x2_a","trailer_variant":"trailer.scs_lowbed_4","trailer_definition":"trailer_def.scs.lowbed.single_4_sh.short","units_count":1,"fill_ratio":1,"trailer_place":0}],"dobr_ferm_bg.pleven":[{"target":"sellplan.prague","urgency":0,"shortest_distance_km":1413,"ferry_time":0,"ferry_price":0,"cargo":"cargo.potatoes","company_truck":"mercedes_actros_2014_4x2_b","trailer_variant":"trailer.scs_dry","trailer_definition":"trailer_def.scs.box.single_3.dryvan","units_count":33,"fill_ratio":1,"trailer_place":0}],"balkan_loco.ruse":[{"target":"kaarfor.poznan","urgency":2,"shortest_distance_km":1620,"ferry_time":0,"ferry_price":0,"cargo":"cargo.mason_jars","company_truck":"mercedes_actros_2014_4x2_c","trailer_variant":"trailer.scs_dry_m","trailer_definition":"trailer_def.scs.box.single_3.dryvan_m","units_count":33,"fill_ratio":1,"trailer_place":0}],"kaarfor.craiova":[{"target":"stokes.poznan","urgency":1,"shortest_distance_km":1347,"ferry_time":0,"ferry_price":0,"cargo":"cargo.used_packag","company_truck":"renault_premium_6x2_a","trailer_variant":"trailer.scs_dry","trailer_definition":"trailer_def.scs.box.single_3.dryvan","units_count":33,"fill_ratio":1,"trailer_place":0}],"st_roza_bg.pernik":[{"target":"lkwlog.venezia","urgency":2,"shortest_distance_km":1716,"ferry_time":0,"ferry_price":0,"cargo":"cargo.largetubes","company_truck":"scania_6x2_b","trailer_variant":"trailer.scs_flat_c_r","trailer_definition":"trailer_def.scs.flatbed.single_3.container","units_count":2,"fill_ratio":1,"trailer_place":0}],"kaarfor.bucuresti":[{"target":"transinet.rotterdam","urgency":1,"shortest_distance_km":2316,"ferry_time":0,"ferry_price":0,"cargo":"cargo.used_plast_c","company_truck":"scania_streamline_6x4_a","trailer_variant":"trailer.scs_flat_c_r","trailer_definition":"trailer_def.scs.flatbed.single_3.container","units_count":33,"fill_ratio":1,"trailer_place":0}],"cnp.constanta":[{"target":"euroacres.brno","urgency":1,"shortest_distance_km":1436,"ferry_time":0,"ferry_price":0,"cargo":"cargo.diesel","company_truck":"iveco_6x2_a","trailer_variant":"trailer.fuel_cistern","trailer_definition":"trailer_def.diesel.fuel_cistern","units_count":94,"fill_ratio":1,"trailer_place":0}],"lognstick.hunedoara":[{"target":"posped.graz","urgency":2,"shortest_distance_km":774,"ferry_time":0,"ferry_price":0,"cargo":"cargo.grapes","company_truck":"renault_magnum_6x2_a","trailer_variant":"trailer.scs_ins_a","trailer_definition":"trailer_def.scs.box.single_3.insulated","units_count":33,"fill_ratio":1,"trailer_place":0},{"target":"transinet.salzburg","urgency":0,"shortest_distance_km":1010,"ferry_time":0,"ferry_price":0,"cargo":"cargo.apples_c","company_truck":"man_6x4_b","trailer_variant":"trailer.scs_gosck20","trailer_definition":"trailer_def.scs.gooseneck.singl_3e_20.container","units_count":15,"fill_ratio":1,"trailer_place":0}],"rimaf.iasi":[{"target":"tradeaux.grimsby","urgency":2,"shortest_distance_km":2899,"ferry_time":35,"ferry_price":300,"cargo":"cargo.milk_t","company_truck":"man_6x4_b","trailer_variant":"trailer.scs_fodt","trailer_definition":"trailer_def.scs.foodtank.single_3.paint","units_count":23,"fill_ratio":1,"trailer_place":0}],"dulcis.pitesti":[{"target":"stokes.poznan","urgency":2,"shortest_distance_km":1533,"ferry_time":0,"ferry_price":0,"cargo":"cargo.empty_palet","company_truck":"renault_t_4x2","trailer_variant":"trailer.scs_dry_a","trailer_definition":"trailer_def.scs.box.single_3.dryvan","units_count":33,"fill_ratio":1,"trailer_place":0}],"kaarfor.ruse":[{"target":"posped.bratislava","urgency":2,"shortest_distance_km":1100,"ferry_time":0,"ferry_price":0,"cargo":"cargo.empty_palet","company_truck":"scania_r_4x2_370","trailer_variant":"trailer.scs_dry","trailer_definition":"trailer_def.scs.box.single_3.dryvan","units_count":33,"fill_ratio":1,"trailer_place":0}],"sporklift.bucuresti":[{"target":"posped.graz","urgency":2,"shortest_distance_km":1114,"ferry_time":0,"ferry_price":0,"cargo":"cargo.used_battery","company_truck":"man_6x4_b","trailer_variant":"trailer.scs_curt","trailer_definition":"trailer_def.scs.box.single_3.curtain","units_count":33,"fill_ratio":1,"trailer_place":0}],"kaarfor.targu_mures":[{"target":"tradeaux.klagenfurt","urgency":0,"shortest_distance_km":1006,"ferry_time":0,"ferry_price":0,"cargo":"cargo.used_plast","company_truck":"mercedes_actros_2014_6x2_a","trailer_variant":"trailer.scs_curt","trailer_definition":"trailer_def.scs.box.single_3.curtain","units_count":33,"fill_ratio":1,"trailer_place":0},{"target":"posped.bremen","urgency":1,"shortest_distance_km":1827,"ferry_time":0,"ferry_price":0,"cargo":"cargo.used_packag","company_truck":"scania_streamline_6x4_a","trailer_variant":"trailer.scs_dry_ms","trailer_definition":"trailer_def.scs.box.single_3.dryvan_m","units_count":33,"fill_ratio":1,"trailer_place":0}],"dobr_ferm_bg.sofia":[{"target":"stokes.amsterdam","urgency":0,"shortest_distance_km":2139,"ferry_time":0,"ferry_price":0,"cargo":"cargo.potatoes","company_truck":"mercedes_actros_2014_6x2_a","trailer_variant":"trailer.scs_dry_a","trailer_definition":"trailer_def.scs.box.single_3.dryvan","units_count":33,"fill_ratio":1,"trailer_place":0}],"cemelt_fla.timisoara":[{"target":"itcc.linz","urgency":0,"shortest_distance_km":743,"ferry_time":0,"ferry_price":0,"cargo":"cargo.emptytank","company_truck":"daf_xf_euro6_4x2_c","trailer_variant":"trailer.scs_flat_r","trailer_definition":"trailer_def.scs.flatbed.single_3.flatbed_w","units_count":2,"fill_ratio":1,"trailer_place":0}],"imp_otel.craiova":[{"target":"tradeaux.lyon","urgency":0,"shortest_distance_km":1961,"ferry_time":0,"ferry_price":0,"cargo":"cargo.vent_tube","company_truck":"daf_xf_euro6_4x2_a","trailer_variant":"trailer.scs_flat_c_r","trailer_definition":"trailer_def.scs.flatbed.single_3.container","units_count":2,"fill_ratio":1,"trailer_place":0}],"st_roza_bg.pirdop":[{"target":"nbfc.linz","urgency":2,"shortest_distance_km":1438,"ferry_time":0,"ferry_price":0,"cargo":"cargo.largetubes","company_truck":"renault_magnum_4x2_a","trailer_variant":"trailer.scs_log","trailer_definition":"trailer_def.scs.log.single_3.steel","units_count":2,"fill_ratio":1,"trailer_place":0}]}